lora_phy/__init__.py
lora_phy/common.py
lora_phy/errors.py
lora_phy/multi.py
lora_phy/plots.py
lora_phy/rx.py
lora_phy/tx.py
lora_phy/typing.py
lora_phy/yaml.py
lora_phy-0.3.0.dist-info/METADATA
lora_phy-0.3.0.dist-info/WHEEL
lora_phy-0.3.0.dist-info/top_level.txt
lora_phy-0.3.0.dist-info/RECORD
