Metadata-Version: 2.4
Name: lora_phy
Version: 0.3.0
Summary: Full implementation of the physical layer of LoRa. (Python translation of jkadbear/LoRaPHY)
Author-email: Zhang Maiyun <maz005@ucsd.edu>, Rohith Reddy Vennam <rvennam@ucsd.edu>
Project-URL: Homepage, https://github.com/myzhang1029/pyLoRaPHY
Project-URL: Issues, https://github.com/myzhang1029/pyLoRaPHY/issues
Classifier: Intended Audience :: Education
Classifier: Intended Audience :: Science/Research
Classifier: Operating System :: OS Independent
Classifier: Programming Language :: Python :: 3
Requires-Python: >=3.8
Requires-Dist: numpy>=1.23.0
Requires-Dist: scipy>=1.9.0
Provides-Extra: yaml
Requires-Dist: pyyaml>=5.4.1; extra == "yaml"
Provides-Extra: plot
Requires-Dist: matplotlib>=3.5.0; extra == "plot"
